{
  "main": {
    "id": "38d1bce8756ef036",
    "type": "split",
    "children": [
      {
        "id": "599644ab774e45de",
        "type": "tabs",
        "children": [
          {
            "id": "a8cc5f7ab2ecf41b",
            "type": "leaf",
            "state": {
              "type": "empty",
              "state": {}
            }
          }
        ]
      }
    ],
    "direction": "vertical"
  },
  "left": {
    "id": "001a1a899531b770",
    "type": "split",
    "children": [
      {
        "id": "6d423fe3a00f983e",
        "type": "tabs",
        "children": [
          {
            "id": "2c7c7641173031ed",
            "type": "leaf",
            "state": {
              "type": "file-explorer",
              "state": {
                "sortOrder": "alphabetical"
              }
            }
          },
          {
            "id": "c639bf84a5b169c1",
            "type": "leaf",
            "state": {
              "type": "search",
              "state": {
                "query": "",
                "matchingCase": false,
                "explainSearch": false,
                "collapseAll": false,
                "extraContext": false,
                "sortOrder": "alphabetical"
              }
            }
          },
          {
            "id": "1a1d1b4d9b03f62a",
            "type": "leaf",
            "state": {
              "type": "bookmarks",
              "state": {}
            }
          }
        ]
      }
    ],
    "direction": "horizontal",
    "width": 300
  },
  "right": {
    "id": "e2c1a34d5dbfa1f5",
    "type": "split",
    "children": [
      {
        "id": "b8e3fb6b804149db",
        "type": "tabs",
        "children": [
          {
            "id": "e9f0c50724af7218",
            "type": "leaf",
            "state": {
              "type": "backlink",
              "state": {
                "collapseAll": false,
                "extraContext": false,
                "sortOrder": "alphabetical",
                "showSearch": false,
                "searchQuery": "",
                "backlinkCollapsed": false,
                "unlinkedCollapsed": true
              }
            }
          },
          {
            "id": "749308521f022a5d",
            "type": "leaf",
            "state": {
              "type": "outgoing-link",
              "state": {
                "linksCollapsed": false,
                "unlinkedCollapsed": true
              }
            }
          },
          {
            "id": "bc33ce3a526b17d6",
            "type": "leaf",
            "state": {
              "type": "tag",
              "state": {
                "sortOrder": "frequency",
                "useHierarchy": true
              }
            }
          },
          {
            "id": "a4274c62677a210b",
            "type": "leaf",
            "state": {
              "type": "outline",
              "state": {}
            }
          }
        ]
      }
    ],
    "direction": "horizontal",
    "width": 300,
    "collapsed": true
  },
  "left-ribbon": {
    "hiddenItems": {
      "switcher:Open quick switcher": false,
      "graph:Open graph view": false,
      "canvas:Create new canvas": false,
      "daily-notes:Open today's daily note": false,
      "templates:Insert template": false,
      "command-palette:Open command palette": false
    }
  },
  "active": "a8cc5f7ab2ecf41b",
  "lastOpenFiles": [
    "_site/welcome-to-jekyll/index.html",
    "_site/welcome-to-jekyll",
    "_site/first-mass-produced/index.html",
    "_site/first-mass-produced",
    "_site/education/index.html",
    "_site/education",
    "_site/acumulated-experience/index.html",
    "_site/acumulated-experience",
    "_site/about-bundler/index.html",
    "_site/about-bundler",
    "_site/we-all-wait-for-summer/index.html",
    "_site/assets/images/screenshot.jpg",
    "_site/assets/images/jekyll.svg",
    "_site/assets/images/home.jpg",
    "_site/assets/images/demo1.jpg",
    "_site/assets/images/avatar2.jpg",
    "_site/assets/images/avatar1.jpg",
    "_site/assets/images/9.jpg",
    "_site/assets/images/8.jpg",
    "_site/assets/images/7.jpg",
    "_site/assets/images/6.jpg",
    "_site/README.md",
    "_posts/2019-02-03-powerful-things-markdown-editor.md",
    "_posts/2019-02-02-first-mass-produced.md",
    "_posts/2019-02-01-education.md",
    "_posts/2019-01-30-acumulated-experience.md",
    "_posts/2019-01-29-about-bundler.md",
    "_posts/2019-01-28-we-all-wait-for-summer.md",
    "_posts/2019-01-27-tree-of-codes.md",
    "_posts/2019-01-26-red-riding.md",
    "_posts/2019-01-25-press-and-education.md",
    "_posts/2019-01-24-powerful-things-markdown-editor.md",
    "_posts/2019-01-23-options-for-creating-new-site-with-jekyll.md",
    "_posts/2019-01-22-never-stopped-worrying-never-loved-bomb.md",
    "_posts/2019-01-21-is-intelligence-enough.md",
    "_posts/2019-01-20-quick-start-guide.md",
    "_posts/2019-01-19-markup-example.md",
    "_posts/2019-01-18-customer-service.md",
    "_posts/2019-01-18-charm-old-cities.md",
    "_pages/privacy-policy.md",
    "_pages/contact.md",
    "_pages/buy-me-a-coffee.md",
    "_pages/about.md",
    "_posts/2024-07-25-welcome-to.md",
    "_posts/2024-07-26-welcome-to-jekyll.md",
    "_posts/testing.md"
  ]
}